dl1_data_handler/__init__.py
dl1_data_handler/_version.py
dl1_data_handler/conftest.py
dl1_data_handler/image_mapper.py
dl1_data_handler/reader.py
dl1_data_handler/tests/test_image_mapper.py
dl1_data_handler/tests/test_reader.py
dl1_data_handler-0.14.7.dist-info/licenses/AUTHORS
dl1_data_handler-0.14.7.dist-info/licenses/LICENSE
dl1_data_handler-0.14.7.dist-info/METADATA
dl1_data_handler-0.14.7.dist-info/WHEEL
dl1_data_handler-0.14.7.dist-info/top_level.txt
dl1_data_handler-0.14.7.dist-info/RECORD
