Metadata-Version: 2.4
Name: dl1_data_handler
Version: 0.14.7
Summary: A package of utilities for reading, and applying image processing to Cherenkov Telescope Array (CTA) R1/DL0/DL1 data in a standardized format. Created primarily for testing machine learning image analysis techniques on IACT data.
Author: Ari Brill, Bryan Kim, Tjark Miener
Author-email: Daniel Nieto <d.nieto@ucm.es>
License: BSD-3-Clause
Project-URL: repository, https://github.com/cta-observatory/dl1-data-handler
Classifier: License :: OSI Approved :: BSD License
Classifier: Intended Audience :: Science/Research
Classifier: Topic :: Scientific/Engineering :: Astronomy
Classifier: Topic :: Scientific/Engineering :: Physics
Classifier: Programming Language :: Python :: 3
Classifier: Programming Language :: Python :: 3.12
Classifier: Programming Language :: Python :: 3.13
Classifier: Programming Language :: Python :: 3.14
Requires-Python: >=3.12
License-File: LICENSE
License-File: AUTHORS
Requires-Dist: ctapipe>=0.28
Requires-Dist: astropy
Requires-Dist: eventio
Requires-Dist: numpy
Requires-Dist: pandas
Requires-Dist: pip
Requires-Dist: pyyaml
Requires-Dist: scipy
Requires-Dist: traitlets
Requires-Dist: pydot
Requires-Dist: setuptools
Provides-Extra: doc
Requires-Dist: sphinx; extra == "doc"
Requires-Dist: sphinx-rtd-theme; extra == "doc"
Provides-Extra: all
Requires-Dist: dl1_data_handler[doc]; extra == "all"
Dynamic: license-file
